<?xml version="1.0" encoding="utf-8"?>
<annotation>
<folder>images</folder>
<filename>669c0168-Sb79c011c26604e58bcd6c15165e01c31A.jpg_720x720q80.jpg</filename>
<source>
<database>MyDatabase</database>
<annotation>COCO2017</annotation>
<image>flickr</image>
<flickrid>NULL</flickrid>
<annotator>1</annotator>
</source>
<owner>
<flickrid>NULL</flickrid>
<name>Label Studio</name>
</owner>
<size>
<width>601</width>
<height>601</height>
<depth>3</depth>
</size>
<segmented>0</segmented>
<object>
<name>Bear Brand Susu Steril (189ml)</name>
<pose>Unspecified</pose>
<truncated>0</truncated>
<difficult>0</difficult>
<bndbox>
<xmin>219</xmin>
<ymin>218</ymin>
<xmax>381</xmax>
<ymax>575</ymax>
</bndbox>
</object>
<object>
<name>Bear Brand Susu Steril (189ml)</name>
<pose>Unspecified</pose>
<truncated>0</truncated>
<difficult>0</difficult>
<bndbox>
<xmin>117</xmin>
<ymin>8</ymin>
<xmax>188</xmax>
<ymax>77</ymax>
</bndbox>
</object>
<object>
<name>Bear Brand Susu Steril (189ml)</name>
<pose>Unspecified</pose>
<truncated>0</truncated>
<difficult>0</difficult>
<bndbox>
<xmin>197</xmin>
<ymin>13</ymin>
<xmax>272</xmax>
<ymax>88</ymax>
</bndbox>
</object>
<object>
<name>Bear Brand Susu Steril (189ml)</name>
<pose>Unspecified</pose>
<truncated>0</truncated>
<difficult>0</difficult>
<bndbox>
<xmin>277</xmin>
<ymin>24</ymin>
<xmax>325</xmax>
<ymax>90</ymax>
</bndbox>
</object>
<object>
<name>Bear Brand Susu Steril (189ml)</name>
<pose>Unspecified</pose>
<truncated>0</truncated>
<difficult>0</difficult>
<bndbox>
<xmin>336</xmin>
<ymin>30</ymin>
<xmax>392</xmax>
<ymax>110</ymax>
</bndbox>
</object>
<object>
<name>Bear Brand Susu Steril (189ml)</name>
<pose>Unspecified</pose>
<truncated>0</truncated>
<difficult>0</difficult>
<bndbox>
<xmin>261</xmin>
<ymin>139</ymin>
<xmax>327</xmax>
<ymax>216</ymax>
</bndbox>
</object>
<object>
<name>Bear Brand Susu Steril (189ml)</name>
<pose>Unspecified</pose>
<truncated>0</truncated>
<difficult>0</difficult>
<bndbox>
<xmin>197</xmin>
<ymin>136</ymin>
<xmax>256</xmax>
<ymax>211</ymax>
</bndbox>
</object>
<object>
<name>Bear Brand Susu Steril (189ml)</name>
<pose>Unspecified</pose>
<truncated>0</truncated>
<difficult>0</difficult>
<bndbox>
<xmin>122</xmin>
<ymin>128</ymin>
<xmax>187</xmax>
<ymax>213</ymax>
</bndbox>
</object>
<object>
<name>Bear Brand Susu Steril (189ml)</name>
<pose>Unspecified</pose>
<truncated>0</truncated>
<difficult>0</difficult>
<bndbox>
<xmin>398</xmin>
<ymin>43</ymin>
<xmax>450</xmax>
<ymax>118</ymax>
</bndbox>
</object>
<object>
<name>Bear Brand Susu Steril (189ml)</name>
<pose>Unspecified</pose>
<truncated>0</truncated>
<difficult>0</difficult>
<bndbox>
<xmin>382</xmin>
<ymin>164</ymin>
<xmax>451</xmax>
<ymax>226</ymax>
</bndbox>
</object>
<object>
<name>Bear Brand Susu Steril (189ml)</name>
<pose>Unspecified</pose>
<truncated>0</truncated>
<difficult>0</difficult>
<bndbox>
<xmin>403</xmin>
<ymin>305</ymin>
<xmax>491</xmax>
<ymax>369</ymax>
</bndbox>
</object>
<object>
<name>Bear Brand Susu Steril (189ml)</name>
<pose>Unspecified</pose>
<truncated>0</truncated>
<difficult>0</difficult>
<bndbox>
<xmin>96</xmin>
<ymin>289</ymin>
<xmax>190</xmax>
<ymax>392</ymax>
</bndbox>
</object>
<object>
<name>Bear Brand Susu Steril (189ml)</name>
<pose>Unspecified</pose>
<truncated>0</truncated>
<difficult>0</difficult>
<bndbox>
<xmin>77</xmin>
<ymin>474</ymin>
<xmax>178</xmax>
<ymax>588</ymax>
</bndbox>
</object>
</annotation>
